scan_models/__init__.py
scan_models/apps.py
scan_models/factory.py
scan_models/main.py
scan_models/management/__init__.py
scan_models/management/commands/__init__.py
scan_models/management/commands/scan_models.py
scan_models/migrations/__init__.py
scan_models/parser/__init__.py
scan_models/parser/attributes.py
scan_models/parser/main.py
scan_models/parser/parser.py
scan_models/parser/validator.py
scan_models/settings.py
scan_models/tests/__init__.py
scan_models/tests/command.py
scan_models/tests/constances.py
scan_models/tests/happy_flow.py
scan_models/tests/parser/__init__.py
scan_models/tests/parser/attributes_parser.py
scan_models/tests/parser/validator_parser.py
scan_models/tests/verbosity.py
scan_models/validators/__init__.py
scan_models/validators/base_validator.py
scan_models/validators/vee_validate.py
scan_models/verbosity.py
django_scan_models-0.2.12.dist-info/LICENSE
django_scan_models-0.2.12.dist-info/WHEEL
django_scan_models-0.2.12.dist-info/METADATA
django_scan_models-0.2.12.dist-info/RECORD
