Metadata-Version: 2.1
Name: django-scan-models
Version: 0.2.12
Summary: Django scan models: Parse django models to frontend validation
Author: Jessie Liauw A Fong
Author-email: jessielaff@live.nl
Requires-Python: >=3.6
Classifier: Development Status :: 5 - Production/Stable
Classifier: Environment :: Console
Classifier: Framework :: Django :: 3.0
Classifier: License :: OSI Approved :: MIT License
Classifier: Programming Language :: Python :: 3
Classifier: Programming Language :: Python :: 3 :: Only
Classifier: Programming Language :: Python :: 3.6
Classifier: Programming Language :: Python :: 3.7
Classifier: Programming Language :: Python :: 3.8
Classifier: Programming Language :: Python :: 3.9
Requires-Dist: django (>=3.0.4,<4.0.0)
